{"packages/cupertino_icons/assets/CupertinoIcons.ttf":["packages/cupertino_icons/assets/CupertinoIcons.ttf"],"fonts/Montserrat-Bold.ttf":["fonts/Montserrat-Bold.ttf"],"fonts/Montserrat-Medium.ttf":["fonts/Montserrat-Medium.ttf"],"fonts/Montserrat-SemiBold.ttf":["fonts/Montserrat-SemiBold.ttf"],"assets/icon-back-arrow-black.png":["assets/icon-back-arrow-black.png"],"assets/icon-back-arrow-white.png":["assets/icon-back-arrow-white.png"],"assets/icon-chat-notification.png":["assets/icon-chat-notification.png"],"assets/icon-favorite.png":["assets/icon-favorite.png"],"assets/icon-home.png":["assets/icon-home.png"],"assets/icon-mentors.png":["assets/icon-mentors.png"],"assets/icon-messages.png":["assets/icon-messages.png"],"assets/icon-search-black.png":["assets/icon-search-black.png"],"assets/icon-search-white.png":["assets/icon-search-white.png"],"assets/icon-selected-rating-star.png":["assets/icon-selected-rating-star.png"],"assets/icon-settings.png":["assets/icon-settings.png"],"assets/icon-unselected-rating-star.png":["assets/icon-unselected-rating-star.png"],"assets/menu-1-yoshimasa-sushi.png":["assets/menu-1-yoshimasa-sushi.png"],"assets/menu-2-yoshimasa-sushi.png":["assets/menu-2-yoshimasa-sushi.png"],"assets/menu-3-prato-sushi.png":["assets/menu-3-prato-sushi.png"],"assets/resturant-1-sushi-den.png":["assets/resturant-1-sushi-den.png"],"assets/resturant-2-hatsuhana-shushi.png":["assets/resturant-2-hatsuhana-shushi.png"],"assets/resturant-3-shushi-maki.png":["assets/resturant-3-shushi-maki.png"]}